survey/__init__.py
survey/admin.py
survey/apps.py
survey/decorators.py
survey/forms.py
survey/locale/ru/LC_MESSAGES/django.mo
survey/locale/ru/LC_MESSAGES/django.po
survey/migrations/0001_initial.py
survey/migrations/0002_survey_template.py
survey/migrations/0003_auto_20170320_0337.py
survey/migrations/0004_polymorphic_answers_to_kiss.py
survey/migrations/0005_rename_question_related_name.py
survey/migrations/0006_add_related_name_for_categories.py
survey/migrations/0007_auto_20180217_1515.py
survey/migrations/0008_translated_name_for_models.py
survey/migrations/0009_auto_20181211_1908.py
survey/migrations/0010_survey_editable_answers.py
survey/migrations/0011_survey_publish_duration.py
survey/migrations/0012_add_display_by_category.py
survey/migrations/0013_auto_20200609_0748.py
survey/migrations/0014_survey_redirect_url.py
survey/migrations/0015_survey_allow_multiple_responses.py
survey/migrations/0016_question_correct_answer.py
survey/migrations/0017_survey_question_content.py
survey/migrations/0018_alter_answer_options_alter_category_options_and_more.py
survey/migrations/__init__.py
survey/models/__init__.py
survey/models/answer.py
survey/models/category.py
survey/models/question.py
survey/models/response.py
survey/models/survey.py
survey/settings.py
survey/signals.py
survey/templates/survey/base.html
survey/templates/survey/forms/image_select.html
survey/templates/survey/question_detail.html
survey/templates/survey/response_detail.html
survey/templates/survey/response_list.html
survey/templates/survey/survey_detail.html
survey/templates/survey/survey_list.html
survey/test_urls.py
survey/tests/__init__.py
survey/tests/admin/__init__.py
survey/tests/admin/test_question.py
survey/tests/base_test.py
survey/tests/factories.py
survey/tests/models/__init__.py
survey/tests/models/base_model_test.py
survey/tests/models/test_answer.py
survey/tests/models/test_category.py
survey/tests/models/test_question.py
survey/tests/models/test_response.py
django_survey_axsapronov-2.0.3.dist-info/LICENSE.txt
django_survey_axsapronov-2.0.3.dist-info/METADATA
django_survey_axsapronov-2.0.3.dist-info/WHEEL
django_survey_axsapronov-2.0.3.dist-info/RECORD
