Metadata-Version: 2.3
Name: django-survey-axsapronov
Version: 2.0.3
Summary: Мощное Django приложение для создания и управления опросами, анкетами и тестами с поддержкой различных типов вопросов, категорий и аналитики
License: AGPL-3.0
Keywords: django,survey,poll,questionnaire,quiz,forms,data-collection,analytics,statistics,web-application
Author: Pierre SASSOULAS
Author-email: pierre.sassoulas@gmail.com
Maintainer: Alexander Sapronov
Maintainer-email: axsapronov@gmail.com
Requires-Python: >=3.12,<3.15
Classifier: Development Status :: 5 - Production/Stable
Classifier: Environment :: Web Environment
Classifier: Framework :: Django
Classifier: Framework :: Django :: 4.0
Classifier: Framework :: Django :: 4.1
Classifier: Framework :: Django :: 4.2
Classifier: Framework :: Django :: 5.0
Classifier: Framework :: Django :: 5.1
Classifier: Framework :: Django :: 5.2
Classifier: Intended Audience :: Developers
Classifier: Intended Audience :: Education
Classifier: Intended Audience :: End Users/Desktop
Classifier: License :: OSI Approved :: GNU Affero General Public License v3
Classifier: Natural Language :: English
Classifier: Natural Language :: Russian
Classifier: Operating System :: OS Independent
Classifier: Programming Language :: Python :: 3
Classifier: Programming Language :: Python :: 3.12
Classifier: Programming Language :: Python :: 3.13
Classifier: Programming Language :: Python :: 3 :: Only
Classifier: Topic :: Internet :: WWW/HTTP :: Dynamic Content
Classifier: Topic :: Software Development :: Libraries :: Python Modules
Classifier: Topic :: Utilities
Classifier: Typing :: Typed
Requires-Dist: crispy-bootstrap5 (>=2025.6,<2026.0)
Requires-Dist: django (>=5.2,<6.0)
Requires-Dist: django-crispy-forms (>=2.4)
Requires-Dist: django-meta (>=2.5.0,<3.0.0)
Requires-Dist: django-pluralize-ru (>=0.1.2,<0.2.0)
Requires-Dist: pytz (>=2025.1,<2026.0)
Requires-Dist: pyyaml (>=6.0.1,<7.0.0)
Project-URL: Documentation, https://github.com/Pierre-Sassoulas/django-survey#readme
Project-URL: Homepage, https://github.com/Pierre-Sassoulas/django-survey
Project-URL: Repository, https://github.com/Pierre-Sassoulas/django-survey
